{
	"type": "FeatureCollection",
	"crs": {
		"type": "name",
		"properties": {
			"name": "urn:ogc:def:crs:OGC:1.3:CRS84"
		}
	},

	"features": [{
			"type": "Feature",
			"properties": {
				"id": 0,
				"Bez": "Geographisches Institut",
				"Syn": "GI, Geographisches Institut",
				"Sekretariat": "Kerstin Schäfer: +492343224788",
				"Studienfachberatung": "Dr. Dennis Edler: +492343223362",
				"Geschäftsführender Direktor": "Prof. Dr. Carsten Jürgens",
				"Zugehörigkeit": "Fakultät für Geowissenschaften"
			},
			"geometry": {
				"type": "Point",
				"coordinates": [7.262467998878375, 51.443086504221256]
			}
		}, {
			"type": "Feature",
			"properties": {
				"id": 1,
				"Bez": "Institut für Geologie, Mineralogie & Geophysik ",
				"Syn": "GMG, Institut für Geologie, Mineralogie & Geophysik",
				"Sekretariat": "Frau Sitter: +49234223233",
				"Studienfachberatung": "Thomas Fockenberg: +492343224392",
				"Geschäftsführender Direktor": "Prof. Dr. Stefan Wohnlich",
				"Zugehörigkeit": "Fakultät für Geowissenschaften"
			},
			"geometry": {
				"type": "Point",
				"coordinates": [7.261779486151085, 51.443848793618244]
			}
		}
	]
}
